pybureaucrat/__init__.py
pybureaucrat/base.py
pybureaucrat/blobs.py
pybureaucrat/bureaucrat_connection.py
pybureaucrat/deserializers.py
pybureaucrat/queues.py
pybureaucrat/tables.py
pybureaucrat/trees.py
pybureaucrat-1.0.15.dist-info/LICENSE
pybureaucrat-1.0.15.dist-info/METADATA
pybureaucrat-1.0.15.dist-info/WHEEL
pybureaucrat-1.0.15.dist-info/top_level.txt
pybureaucrat-1.0.15.dist-info/RECORD
