Metadata-Version: 2.1
Name: pybureaucrat
Version: 1.0.15
Summary: A python client for bureaucrat server
Home-page: https://github.com/LostSavannah/bureaucrat/tree/main/lib
Author: Erick Fernando Mora Ramirez
Author-email: erickfernandomoraramirez@gmail.com
Project-URL: Bug Tracker, https://dev.moradev.dev/pybureaucrat/issues
Project-URL: Documentation, https://dev.moradev.dev/pybureaucrat/documentation
Project-URL: Examples, https://dev.moradev.dev/pybureaucrat/examples
Classifier: Programming Language :: Python :: 3
Classifier: Development Status :: 5 - Production/Stable
Classifier: License :: OSI Approved :: GNU General Public License v3 (GPLv3)
Classifier: Operating System :: OS Independent
Requires-Python: >=3.6
License-File: LICENSE
